odoo/addons/account_move_line_report_xls/README.rst
odoo/addons/account_move_line_report_xls/__init__.py
odoo/addons/account_move_line_report_xls/__manifest__.py
odoo/addons/account_move_line_report_xls/i18n/account_move_line_report_xls.pot
odoo/addons/account_move_line_report_xls/i18n/fr.po
odoo/addons/account_move_line_report_xls/i18n/nl.po
odoo/addons/account_move_line_report_xls/models/__init__.py
odoo/addons/account_move_line_report_xls/models/account_move_line.py
odoo/addons/account_move_line_report_xls/readme/CONTRIBUTORS.rst
odoo/addons/account_move_line_report_xls/readme/DESCRIPTION.rst
odoo/addons/account_move_line_report_xls/readme/USAGE.rst
odoo/addons/account_move_line_report_xls/report/__init__.py
odoo/addons/account_move_line_report_xls/report/account_move_line_xlsx.py
odoo/addons/account_move_line_report_xls/report/account_move_line_xlsx.xml
odoo/addons/account_move_line_report_xls/static/description/icon.png
odoo/addons/account_move_line_report_xls/static/description/icon.svg
odoo/addons/account_move_line_report_xls/static/description/index.html
odoo/addons/account_move_line_report_xls/tests/__init__.py
odoo/addons/account_move_line_report_xls/tests/test_aml_report_xlsx.py
odoo14_addon_account_move_line_report_xls-14.0.1.0.1.dist-info/METADATA
odoo14_addon_account_move_line_report_xls-14.0.1.0.1.dist-info/WHEEL
odoo14_addon_account_move_line_report_xls-14.0.1.0.1.dist-info/top_level.txt
odoo14_addon_account_move_line_report_xls-14.0.1.0.1.dist-info/RECORD
